fdq/__about__.py
fdq/__init__.py
fdq/dataset_caching.py
fdq/dump.py
fdq/experiment.py
fdq/inference.py
fdq/misc.py
fdq/run_experiment.py
fdq/tensorrt_engine.py
fdq/testing.py
fdq/transformers.py
fdq/ui_functions.py
fdq-0.0.75.dist-info/METADATA
fdq-0.0.75.dist-info/WHEEL
fdq-0.0.75.dist-info/entry_points.txt
fdq-0.0.75.dist-info/licenses/LICENSE
fdq-0.0.75.dist-info/RECORD
