Metadata-Version: 2.4
Name: fdq
Version: 0.0.75
Summary: ML runtime (https://pypi.org/project/fdq/)
Project-URL: Homepage, https://github.com/mstadelmann/fonduecaquelon
Project-URL: Repository, https://github.com/mstadelmann/fonduecaquelon.git
Project-URL: Issues, https://github.com/mstadelmann/fonduecaquelon/issues
Author-email: Marc Stadelmann <stdma@pm.me>
Maintainer-email: Marc Stadelmann <stdma@pm.me>
License: GPL-3.0-or-later
License-File: LICENSE
Classifier: Operating System :: OS Independent
Classifier: Programming Language :: Python :: 3
Requires-Python: <3.13,>=3.10
Requires-Dist: colorama==0.4.6
Requires-Dist: einops==0.8.1
Requires-Dist: funkybob==2023.12.0
Requires-Dist: h5py==3.13.0
Requires-Dist: hydra-core>=1.3.2
Requires-Dist: matplotlib==3.10.1
Requires-Dist: onnxruntime==1.22.1
Requires-Dist: opencv-python==4.11.0.86
Requires-Dist: progressbar==2.5
Requires-Dist: scikit-learn==1.6.1
Requires-Dist: tensorboard==2.19.0
Requires-Dist: termcolor==3.1.0
Requires-Dist: termplotlib==0.3.9
Requires-Dist: torch==2.7.0
Requires-Dist: torchview==0.2.7
Requires-Dist: torchvision==0.22.0
Requires-Dist: tpl==0.10
Requires-Dist: tqdm==4.67.1
Requires-Dist: wandb==0.19.10
Provides-Extra: dev
Requires-Dist: ruff==0.11.8; extra == 'dev'
Provides-Extra: gpu
Requires-Dist: pycuda==2025.1.1; extra == 'gpu'
Requires-Dist: torch-tensorrt==2.7.0; extra == 'gpu'
